pystra/__init__.py
pystra/analysis.py
pystra/calibration.py
pystra/correlation.py
pystra/form.py
pystra/integration.py
pystra/loadcomb.py
pystra/mc.py
pystra/model.py
pystra/quadrature.py
pystra/sensitivity.py
pystra/sorm.py
pystra/transformation.py
pystra/distributions/__init__.py
pystra/distributions/beta.py
pystra/distributions/chisquare.py
pystra/distributions/distribution.py
pystra/distributions/gamma.py
pystra/distributions/gumbel.py
pystra/distributions/lognormal.py
pystra/distributions/maximum.py
pystra/distributions/normal.py
pystra/distributions/parent.py
pystra/distributions/scipydist.py
pystra/distributions/shiftedexponential.py
pystra/distributions/shiftedrayleigh.py
pystra/distributions/typeiiismallestvalue.py
pystra/distributions/typeiilargestvalue.py
pystra/distributions/typeilargestvalue.py
pystra/distributions/typeismallestvalue.py
pystra/distributions/uniform.py
pystra/distributions/weibull.py
pystra/distributions/zeroinflated.py
Pystra-1.3.0.dist-info/LICENSE
Pystra-1.3.0.dist-info/METADATA
Pystra-1.3.0.dist-info/WHEEL
Pystra-1.3.0.dist-info/top_level.txt
Pystra-1.3.0.dist-info/RECORD
