Metadata-Version: 2.1
Name: Pystra
Version: 1.3.0
Summary: Python Structural Reliability Analysis
Author-email: Colin Caprani <colin.caprani@monash.edu>, "M. Shihab Khan" <shihab.khan@monash.edu>, Jürgen Hackl <hackl.science@gmail.com>
License: Apache 2.0
Project-URL: Homepage, https://pystra.github.io/pystra/
Project-URL: Documentation, https://pystra.github.io/pystra/
Project-URL: Source, https://github.com/pystra/pystra/
Project-URL: Tracker, https://github.com/pystra/pystra/issues/
Keywords: structural,reliability,engineering
Platform: any
Classifier: Development Status :: 4 - Beta
Classifier: Topic :: Scientific/Engineering
Classifier: Environment :: Console
Classifier: Intended Audience :: Science/Research
Classifier: Programming Language :: Python :: 3 :: Only
Classifier: License :: OSI Approved :: Apache Software License
Classifier: Natural Language :: English
Classifier: Operating System :: POSIX :: Linux
Classifier: Operating System :: MacOS :: MacOS X
Classifier: Operating System :: Microsoft :: Windows
Classifier: Programming Language :: Python :: 3.8
Classifier: Programming Language :: Python :: 3.9
Classifier: Programming Language :: Python :: 3.10
Classifier: Programming Language :: Python :: 3.11
Requires-Python: >=3.8
License-File: LICENSE
Requires-Dist: matplotlib
Requires-Dist: numpy
Requires-Dist: scipy
Requires-Dist: pandas
Provides-Extra: test
Requires-Dist: pytest >=6.2.2 ; extra == 'test'
